{"gameKey":{"gameId":327752468,"platformId":"BR1"},"gameServerAddress":"","port":0,"encryptionKey":"5h8ZW/TGg3jiVL5ao3K+oQmJ2bepgY5m","chunkTimeInterval":30000,"startTime":"Dec 31, 1969 4:00:00 PM","gameEnded":false,"lastChunkId":2,"lastKeyFrameId":-1,"endStartupChunkId":1,"delayTime":150000,"pendingAvailableChunkInfo":[{"id":1,"duration":13794,"receivedTime":"Aug 3, 2014 8:39:04 AM"},{"id":2,"duration":1,"receivedTime":"Aug 3, 2014 8:39:06 AM"}],"pendingAvailableKeyFrameInfo":[],"keyFrameTimeInterval":60000,"decodedEncryptionKey":"","startGameChunkId":0,"gameLength":0,"clientAddedLag":30000,"clientBackFetchingEnabled":false,"clientBackFetchingFreq":1000,"interestScore":0,"featuredGame":false,"createTime":"Aug 3, 2014 8:38:52 AM","endGameChunkId":-1,"endGameKeyFrameId":-1}